dbt/adapters/spark_livy/.env
dbt/adapters/spark_livy/__init__.py
dbt/adapters/spark_livy/__version__.py
dbt/adapters/spark_livy/cloudera_tracking.py
dbt/adapters/spark_livy/column.py
dbt/adapters/spark_livy/connections.py
dbt/adapters/spark_livy/impl.py
dbt/adapters/spark_livy/livysession.py
dbt/adapters/spark_livy/python_submissions.py
dbt/adapters/spark_livy/relation.py
dbt/adapters/spark_livy/session.py
dbt/include/spark_livy/__init__.py
dbt/include/spark_livy/dbt_project.yml
dbt/include/spark_livy/profile_template.yml
dbt/include/spark_livy/macros/adapters.sql
dbt/include/spark_livy/macros/apply_grants.sql
dbt/include/spark_livy/macros/materializations/seed.sql
dbt/include/spark_livy/macros/materializations/snapshot.sql
dbt/include/spark_livy/macros/materializations/table.sql
dbt/include/spark_livy/macros/materializations/view.sql
dbt/include/spark_livy/macros/materializations/incremental/column_helpers.sql
dbt/include/spark_livy/macros/materializations/incremental/incremental.sql
dbt/include/spark_livy/macros/materializations/incremental/strategies.sql
dbt/include/spark_livy/macros/materializations/incremental/validate.sql
dbt/include/spark_livy/macros/utils/any_value.sql
dbt/include/spark_livy/macros/utils/array_append.sql
dbt/include/spark_livy/macros/utils/array_concat.sql
dbt/include/spark_livy/macros/utils/array_construct.sql
dbt/include/spark_livy/macros/utils/assert_not_null.sql
dbt/include/spark_livy/macros/utils/bool_or.sql
dbt/include/spark_livy/macros/utils/concat.sql
dbt/include/spark_livy/macros/utils/dateadd.sql
dbt/include/spark_livy/macros/utils/datediff.sql
dbt/include/spark_livy/macros/utils/intersect.sql
dbt/include/spark_livy/macros/utils/listagg.sql
dbt/include/spark_livy/macros/utils/split_part.sql
dbt/include/spark_livy/macros/utils/timestamps.sql
dbt_spark_livy-1.3.1.data/data/.env
dbt_spark_livy-1.3.1.dist-info/METADATA
dbt_spark_livy-1.3.1.dist-info/WHEEL
dbt_spark_livy-1.3.1.dist-info/top_level.txt
dbt_spark_livy-1.3.1.dist-info/RECORD
