Metadata-Version: 2.1
Name: dbt-spark-livy
Version: 1.3.1
Summary: The dbt-spark-livy adapter plugin for Spark in Cloudera DataHub with Livy interface
Home-page: https://github.com/cloudera/dbt-spark-livy
Author: Cloudera
Author-email: innovation-feedback@cloudera.com
Classifier: Development Status :: 5 - Production/Stable
Classifier: License :: OSI Approved :: Apache Software License
Classifier: Operating System :: Microsoft :: Windows
Classifier: Operating System :: MacOS :: MacOS X
Classifier: Operating System :: POSIX :: Linux
Classifier: Programming Language :: Python :: 3.7
Classifier: Programming Language :: Python :: 3.8
Classifier: Programming Language :: Python :: 3.9
Requires-Python: >=3.7
Requires-Dist: dbt-core (~=1.3.0)
Requires-Dist: sqlparams (>=3.0.0)
Requires-Dist: requests-kerberos (==0.14)
Requires-Dist: requests-toolbelt (>=0.9.1)
Requires-Dist: python-decouple (>=3.6)
Provides-Extra: odbc
Requires-Dist: pyodbc (>=4.0.30) ; extra == 'odbc'
Provides-Extra: pyhive
Requires-Dist: PyHive[hive] (<0.7.0,>=0.6.0) ; extra == 'pyhive'
Requires-Dist: thrift (<0.16.0,>=0.11.0) ; extra == 'pyhive'
Provides-Extra: all
Requires-Dist: pyodbc (>=4.0.30) ; extra == 'all'
Requires-Dist: PyHive[hive] (<0.7.0,>=0.6.0) ; extra == 'all'
Requires-Dist: thrift (<0.16.0,>=0.11.0) ; extra == 'all'
Requires-Dist: pyspark (<4.0.0,>=3.0.0) ; extra == 'all'
Provides-Extra: session
Requires-Dist: pyspark (<4.0.0,>=3.0.0) ; extra == 'session'
